{
  "0": [
    {
      "71": {
        "0": [
          4,
          "{Numpad7}",
          1,
          null,
          0,
          0,
          0,
          0,
          null,
          {},
          {}
        ]
      },
      "72": {
        "0": [
          4,
          "{Numpad8}",
          1,
          null,
          0,
          0,
          0,
          0,
          null,
          {},
          {}
        ]
      },
      "73": {
        "0": [
          4,
          "{Numpad9}",
          1,
          null,
          0,
          0,
          0,
          0,
          null,
          {},
          {}
        ]
      },
      "75": {
        "0": [
          4,
          "{Numpad4}",
          1,
          null,
          0,
          0,
          0,
          0,
          null,
          {},
          {}
        ]
      },
      "76": {
        "0": [
          4,
          "{Numpad5}",
          1,
          null,
          0,
          0,
          0,
          0,
          null,
          {},
          {}
        ]
      },
      "77": {
        "0": [
          4,
          "{Numpad6}",
          1,
          null,
          0,
          0,
          0,
          0,
          null,
          {},
          {}
        ]
      },
      "79": {
        "0": [
          4,
          "{Numpad1}",
          1,
          null,
          0,
          0,
          0,
          0,
          null,
          {},
          {}
        ]
      },
      "80": {
        "0": [
          4,
          "{Numpad2}",
          1,
          null,
          0,
          0,
          0,
          0,
          null,
          {},
          {}
        ]
      },
      "81": {
        "0": [
          4,
          "{Numpad3}",
          1,
          null,
          0,
          0,
          0,
          0,
          null,
          {},
          {}
        ]
      },
      "82": {
        "0": [
          4,
          "{Numpad0}",
          1,
          null,
          0,
          0,
          0,
          0,
          null,
          {},
          {}
        ]
      },
      "83": {
        "0": [
          4,
          "{NumpadDot}",
          1,
          null,
          0,
          0,
          0,
          0,
          null,
          {},
          {}
        ]
      }
    },
    {}
  ]
}